sara/__init__.py
sara/core.py
sara_karts-0.1.0.dist-info/licenses/LICENSE
sara_karts-0.1.0.dist-info/METADATA
sara_karts-0.1.0.dist-info/WHEEL
sara_karts-0.1.0.dist-info/top_level.txt
sara_karts-0.1.0.dist-info/RECORD
