Metadata-Version: 2.4
Name: sara-karts
Version: 0.1.0
Summary: Sara - An AI-powered code generator assistant
Home-page: https://github.com/yourusername/sara
Author: Karthick Anandh RJ
Author-email: karthickanandh1304@gmail.com
Classifier: Programming Language :: Python :: 3
Classifier: License :: OSI Approved :: MIT License
Classifier: Operating System :: OS Independent
Requires-Python: >=3.7
License-File: LICENSE
Requires-Dist: pydantic<3.0,>=2.0
Dynamic: author
Dynamic: author-email
Dynamic: classifier
Dynamic: description
Dynamic: description-content-type
Dynamic: home-page
Dynamic: license-file
Dynamic: requires-dist
Dynamic: requires-python
Dynamic: summary
